lgsvl_tools/urdf_generator.py
lgsvl_tools-0.1.7.dist-info/LICENSE.txt
lgsvl_tools-0.1.7.dist-info/METADATA
lgsvl_tools-0.1.7.dist-info/WHEEL
lgsvl_tools-0.1.7.dist-info/entry_points.txt
lgsvl_tools-0.1.7.dist-info/top_level.txt
lgsvl_tools-0.1.7.dist-info/RECORD
